[
  {
    "context": "Editor",
    "bindings": {
      "ctrl-j": "workspace::ToggleBottomDock"
    }
  },
  {
    "context": "Workspace",
    "bindings": {
      "ctrl-l": ["workspace::SendKeystrokes", "ctrl-` ! ! enter"],
      "ctrl-shift-c": null
    }
  },
  {
    "context": "Dock",
    "bindings": {
      "ctrl-shift-c": null
    }
  },
  {
    "bindings": {
      "ctrl-shift-c": null
    }
  },
  {
    "context": "VimControl && !menu",
    "bindings": {
      "ctrl-l": ["workspace::SendKeystrokes", "ctrl-` ! ! enter"]
    }
  },
  {
    "context": "vim_mode == insert",
    "bindings": {
      "ctrl-l": ["workspace::SendKeystrokes", "ctrl-` ! ! enter"]
    }
  }
]
